rut-0.2.1.dist-info/licenses/LICENSE
rutlib/__init__.py
rutlib/__main__.py
rutlib/cli.py
rutlib/runner.py
rut-0.2.1.dist-info/METADATA
rut-0.2.1.dist-info/WHEEL
rut-0.2.1.dist-info/entry_points.txt
rut-0.2.1.dist-info/top_level.txt
rut-0.2.1.dist-info/RECORD
