Metadata-Version: 2.4
Name: rut
Version: 0.2.1
Summary: A test runner for python unittest with async support.
Author-email: Eduardo Naufel Schettino <schettino72@gmail.com>
License-Expression: MIT
Project-URL: Homepage, https://github.com/schettino72/rut
Project-URL: Source, https://github.com/schettino72/rut
Keywords: test,unittest,async
Classifier: Development Status :: 4 - Beta
Classifier: Operating System :: OS Independent
Classifier: Programming Language :: Python :: 3
Classifier: Programming Language :: Python :: 3.12
Classifier: Programming Language :: Python :: 3.13
Classifier: Topic :: Software Development :: Testing
Requires-Python: >=3.12
License-File: LICENSE
Requires-Dist: coverage
Dynamic: license-file
